domino_code_assist/DominoLogoGrey.svg
domino_code_assist/DominoLogoWhite.svg
domino_code_assist/__init__.py
domino_code_assist/action.py
domino_code_assist/action_ui.py
domino_code_assist/actions_store.py
domino_code_assist/app.py
domino_code_assist/app_entrypoint.py
domino_code_assist/code.py
domino_code_assist/code.vue
domino_code_assist/components.py
domino_code_assist/crossfilter_widgets.py
domino_code_assist/css.py
domino_code_assist/css.vue
domino_code_assist/df_select.py
domino_code_assist/df_select.vue
domino_code_assist/domino_api.py
domino_code_assist/domino_api_mock_data.py
domino_code_assist/domino_lab_mock.py
domino_code_assist/express.py
domino_code_assist/hooks.py
domino_code_assist/layout.py
domino_code_assist/logging_workaround.py
domino_code_assist/nb_app.py
domino_code_assist/py36.py
domino_code_assist/sample_project_md.py
domino_code_assist/serialize.py
domino_code_assist/settings.py
domino_code_assist/thumbnail.py
domino_code_assist/util.py
domino_code_assist/widgets.py
domino_code_assist/assistant/__init__.py
domino_code_assist/assistant/assistant.py
domino_code_assist/assistant/assistant.vue
domino_code_assist/assistant/drawer.py
domino_code_assist/assistant/drawer.vue
domino_code_assist/assistant/handle_user_install.py
domino_code_assist/assistant/menu.vue
domino_code_assist/assistant/mixpanel.py
domino_code_assist/assistant/mixpanel.vue
domino_code_assist/assistant/notebook.py
domino_code_assist/automl/__init__.py
domino_code_assist/automl/above_output.vue
domino_code_assist/automl/code.py
domino_code_assist/automl/drawer.py
domino_code_assist/automl/experiment_search.py
domino_code_assist/automl/experiment_search.vue
domino_code_assist/automl/flaml_api.py
domino_code_assist/automl/hyper_parameters.py
domino_code_assist/automl/icon_classification.svg
domino_code_assist/automl/icon_forecasting.svg
domino_code_assist/automl/icon_regression.svg
domino_code_assist/automl/open_experiment.py
domino_code_assist/automl/placeholder.png
domino_code_assist-1.4.1.dist-info/METADATA
domino_code_assist-1.4.1.dist-info/WHEEL
domino_code_assist-1.4.1.dist-info/licenses/LICENSE.md
domino_code_assist-1.4.1.dist-info/RECORD
