Metadata-Version: 2.1
Name: domino-code-assist
Version: 1.4.1
Project-URL: Home, https://github.com/cerebrotech/domino-code-assist
License-File: LICENSE.md
Requires-Dist: accelerate==0.19.0
Requires-Dist: albumentations
Requires-Dist: attrs<22.0.0
Requires-Dist: datasets==2.12.0
Requires-Dist: dominodatalab; python_version >= '3.8'
Requires-Dist: evaluate
Requires-Dist: flaml
Requires-Dist: flaml[catboost]
Requires-Dist: hcrystalball
Requires-Dist: humanize
Requires-Dist: ipyvue
Requires-Dist: ipyvuetify>=1.8.5
Requires-Dist: ipywidgets<8
Requires-Dist: lightgbm
Requires-Dist: mlflow>=2.4
Requires-Dist: nbformat>=4.5
Requires-Dist: nltk
Requires-Dist: notebook>=4.6
Requires-Dist: openpyxl
Requires-Dist: pandas
Requires-Dist: plotly>=5.5
Requires-Dist: pydantic
Requires-Dist: reacton~=1.6.0
Requires-Dist: rouge-score
Requires-Dist: seqeval
Requires-Dist: solara[assets]~=1.13.0
Requires-Dist: statsmodels
Requires-Dist: timm
Requires-Dist: torch==2.0.1
Requires-Dist: torchvision
Requires-Dist: transformers<=4.29.2
Requires-Dist: vaex-core
Requires-Dist: xlrd
Provides-Extra: dev
Requires-Dist: black; extra == 'dev'
Requires-Dist: bump2version; extra == 'dev'
Requires-Dist: dominodatalab-data; extra == 'dev'
Requires-Dist: flake8; extra == 'dev'
Requires-Dist: playwright==1.19.0; extra == 'dev'
Requires-Dist: pre-commit; extra == 'dev'
Requires-Dist: pytest; extra == 'dev'
Requires-Dist: pytest-cov; extra == 'dev'
Requires-Dist: pytest-mock; extra == 'dev'
Requires-Dist: pytest-playwright; extra == 'dev'
Requires-Dist: pytest-timeout; extra == 'dev'
Requires-Dist: python-dotenv; extra == 'dev'
Requires-Dist: redshift-connector; extra == 'dev'
Requires-Dist: snowflake-connector-python<3.0; extra == 'dev'
Requires-Dist: types-requests; extra == 'dev'
